siaql/__init__.py
siaql/api/__init__.py
siaql/api/hostd.py
siaql/api/renterd.py
siaql/api/utils.py
siaql/api/walletd.py
siaql/cli/__init__.py
siaql/cli/main.py
siaql/graphql/__init__.py
siaql/graphql/app.py
siaql/graphql/resolvers/__init__.py
siaql/graphql/resolvers/converter.py
siaql/graphql/resolvers/filter.py
siaql/graphql/resolvers/hostd.py
siaql/graphql/resolvers/renterd.py
siaql/graphql/resolvers/walletd.py
siaql/graphql/schema.py
siaql/graphql/schemas/__init__.py
siaql/graphql/schemas/hostd/__init__.py
siaql/graphql/schemas/hostd/accounts.py
siaql/graphql/schemas/hostd/alerts.py
siaql/graphql/schemas/hostd/consensus.py
siaql/graphql/schemas/hostd/contracts.py
siaql/graphql/schemas/hostd/index.py
siaql/graphql/schemas/hostd/metrics.py
siaql/graphql/schemas/hostd/sectors.py
siaql/graphql/schemas/hostd/settings.py
siaql/graphql/schemas/hostd/state.py
siaql/graphql/schemas/hostd/syncer.py
siaql/graphql/schemas/hostd/system.py
siaql/graphql/schemas/hostd/tpool.py
siaql/graphql/schemas/hostd/volumes.py
siaql/graphql/schemas/hostd/wallet.py
siaql/graphql/schemas/hostd/webhooks.py
siaql/graphql/schemas/renterd/__init__.py
siaql/graphql/schemas/renterd/autopilot.py
siaql/graphql/schemas/renterd/bus.py
siaql/graphql/schemas/renterd/worker.py
siaql/graphql/schemas/types.py
siaql/graphql/schemas/walletd/__init__.py
siaql/graphql/schemas/walletd/addresses.py
siaql/graphql/schemas/walletd/consensus.py
siaql/graphql/schemas/walletd/events.py
siaql/graphql/schemas/walletd/outputs.py
siaql/graphql/schemas/walletd/rescan.py
siaql/graphql/schemas/walletd/state.py
siaql/graphql/schemas/walletd/syncer.py
siaql/graphql/schemas/walletd/txpool.py
siaql/graphql/schemas/walletd/wallets.py
siaql/logging_config.py
siaql/scripts/build_docs.py
siaql-0.1.1.dist-info/LICENSE
siaql-0.1.1.dist-info/METADATA
siaql-0.1.1.dist-info/WHEEL
siaql-0.1.1.dist-info/entry_points.txt
siaql-0.1.1.dist-info/RECORD
