Metadata-Version: 2.3
Name: siaql
Version: 0.1.1
Summary: GraphQL interface for Sia network components
Author: Mert Köklü
Author-email: kklumert@gmail.com
Requires-Python: >=3.9,<4.0
Classifier: Programming Language :: Python :: 3
Classifier: Programming Language :: Python :: 3.9
Classifier: Programming Language :: Python :: 3.10
Classifier: Programming Language :: Python :: 3.11
Classifier: Programming Language :: Python :: 3.12
Classifier: Programming Language :: Python :: 3.13
Requires-Dist: httpx (>=0.27.2,<0.28.0)
Requires-Dist: rich (>=13.9.4,<14.0.0)
Requires-Dist: strawberry-graphql[debug-server] (>=0.258.0,<0.259.0)
Requires-Dist: typer[all] (>=0.9.4,<0.10.0)
Requires-Dist: uvicorn[standard] (>=0.27.0,<0.28.0)
